linphone/__init__.py
linphone/linphone.so
linphone/libavcodec.so.53
linphone/libavutil.so.51
linphone/libswscale.so.2
linphone/share/images/nowebcamCIF.jpg
linphone/share/linphone/rootca.pem
linphone/share/sounds/linphone/hello16000.wav
linphone/share/sounds/linphone/hello8000.wav
linphone/share/sounds/linphone/incoming_chat.wav
linphone/share/sounds/linphone/ringback.wav
linphone/share/sounds/linphone/rings/bigben.wav
linphone/share/sounds/linphone/rings/oldphone-mono-30s.caf
linphone/share/sounds/linphone/rings/oldphone-mono.wav
linphone/share/sounds/linphone/rings/oldphone.wav
linphone/share/sounds/linphone/rings/orig.wav
linphone/share/sounds/linphone/rings/rock.wav
linphone/share/sounds/linphone/rings/sweet.wav
linphone/share/sounds/linphone/rings/synth.wav
linphone/share/sounds/linphone/rings/tapping.wav
linphone/share/sounds/linphone/rings/toy-mono.wav
linphone/unittests/README.txt
linphone/unittests/linphonetester.py
linphone/unittests/test_call.py
linphone/unittests/test_message.py
linphone/unittests/test_presence.py
linphone/unittests/test_register.py
linphone/unittests/test_setup.py
linphone/unittests/tester_hosts
linphone/unittests/certificates/altname/agent.pem
linphone/unittests/certificates/altname/cafile.pem
linphone/unittests/certificates/altname/openssl-altname.cnf
linphone/unittests/certificates/cn/agent.pem
linphone/unittests/certificates/cn/cafile.pem
linphone/unittests/certificates/cn/openssl-cn.cnf
linphone/unittests/images/nowebcamCIF.jpg
linphone/unittests/rcfiles/empty_rc
linphone/unittests/rcfiles/laure_call_logs_rc
linphone/unittests/rcfiles/laure_rc
linphone/unittests/rcfiles/marie_early_rc
linphone/unittests/rcfiles/marie_h264_rc
linphone/unittests/rcfiles/marie_quality_reporting_rc
linphone/unittests/rcfiles/marie_rc
linphone/unittests/rcfiles/marie_rc_rtcp_xr
linphone/unittests/rcfiles/marie_remote_404_rc
linphone/unittests/rcfiles/marie_remote_default_values_rc
linphone4raspberry-3.9.0.dist-info/zip-safe
linphone4raspberry-3.9.0.dist-info/top_level.txt
linphone4raspberry-3.9.0.dist-info/METADATA
linphone4raspberry-3.9.0.dist-info/DESCRIPTION.rst
linphone4raspberry-3.9.0.dist-info/metadata.json
linphone4raspberry-3.9.0.dist-info/WHEEL
linphone4raspberry-3.9.0.dist-info/RECORD
