Metadata-Version: 2.0
Name: linphone4raspberry
Version: 3.9.0
Summary: Linphone package for Python
Home-page: http://www.linphone.org/
Author: Belledonne Communications
Author-email: contact@belledonne-communications.com
License: UNKNOWN
Keywords: sip,voip
Platform: UNKNOWN
Classifier: Development Status :: 5 - Production/Stable
Classifier: Environment :: Other Environment
Classifier: Intended Audience :: Developers
Classifier: Intended Audience :: Telecommunications Industry
Classifier: License :: OSI Approved :: GNU General Public License v2 or later (GPLv2+)
Classifier: Natural Language :: English
Classifier: Operating System :: Microsoft :: Windows
Classifier: Programming Language :: C
Classifier: Programming Language :: C++
Classifier: Programming Language :: Python :: 2.7
Classifier: Topic :: Communications :: Chat
Classifier: Topic :: Communications :: Internet Phone
Classifier: Topic :: Communications :: Telephony
